PolyNum/NumericalMethods.py
PolyNum/Polynomial.py
PolyNum/__init__.py
PolyNum-0.2.dist-info/METADATA
PolyNum-0.2.dist-info/WHEEL
PolyNum-0.2.dist-info/top_level.txt
PolyNum-0.2.dist-info/RECORD
