Metadata-Version: 2.1
Name: PolyNum
Version: 0.2
Summary: UNKNOWN
Home-page: UNKNOWN
Author: Muskan Chaurasia
License: UNKNOWN
Platform: UNKNOWN
